{
  "minecraft:story/obtain_armor": {
    "criteria": {
      "iron_chestplate": "2024-10-30 17:29:05 -0700",
      "iron_leggings": "2024-10-30 17:29:05 -0700"
    },
    "done": true
  },
  "minecraft:story/iron_tools": {
    "criteria": {
      "iron_pickaxe": "2024-10-30 17:29:05 -0700"
    },
    "done": true
  },
  "minecraft:adventure/root": {
    "criteria": {
      "killed_something": "2024-10-30 17:30:05 -0700"
    },
    "done": true
  },
  "minecraft:adventure/adventuring_time": {
    "criteria": {
      "ice_flats": "2024-10-30 17:29:05 -0700",
      "ice_mountains": "2024-10-30 17:31:38 -0700"
    },
    "done": false
  }
}